django_open_ai/__init__.py
django_open_ai/admin.py
django_open_ai/apps.py
django_open_ai/forms.py
django_open_ai/helper.py
django_open_ai/models.py
django_open_ai/tests.py
django_open_ai/views.py
django_open_ai/migrations/__init__.py
django_open_ai/templates/form.html
django_open_ai-0.1.0.dist-info/LICENSE
django_open_ai-0.1.0.dist-info/METADATA
django_open_ai-0.1.0.dist-info/WHEEL
django_open_ai-0.1.0.dist-info/top_level.txt
django_open_ai-0.1.0.dist-info/RECORD
