Metadata-Version: 2.1
Name: django-open-ai
Version: 0.1.0
Summary: Use the power of OpenAI on your Django database
Home-page: https://github.com/PMCS64/django-open-ai
License: MIT
Classifier: Development Status :: 4 - Beta
Classifier: Environment :: Web Environment
Classifier: Intended Audience :: Developers
Classifier: License :: OSI Approved :: MIT License
Classifier: Operating System :: OS Independent
Classifier: Programming Language :: Python :: 3 :: Only
Classifier: Programming Language :: Python :: 3.10
Classifier: Programming Language :: Python :: Implementation :: CPython
Classifier: Topic :: Software Development :: Libraries :: Application Frameworks
Classifier: Topic :: Software Development :: Libraries :: Python Modules
Requires-Python: >=3.10
License-File: LICENSE
Requires-Dist: Django (>=4.2)
Requires-Dist: sqlalchemy (>=2.0.19)
Requires-Dist: openai (>=0.27.8)
Requires-Dist: langchain (>=0.0.238)
